alea_data_generator/__init__.py
alea_data_generator/cli/__init__.py
alea_data_generator/cli/generate_homophones.py
alea_data_generator/conversions/__init__.py
alea_data_generator/data/__init__.py
alea_data_generator/data/constants/__init__.py
alea_data_generator/data/constants/keyboard.py
alea_data_generator/data/constants/ocr.py
alea_data_generator/perturbations/__init__.py
alea_data_generator/perturbations/errors/__init__.py
alea_data_generator/perturbations/errors/config.py
alea_data_generator/perturbations/errors/encoding/__init__.py
alea_data_generator/perturbations/errors/methods/__init__.py
alea_data_generator/perturbations/errors/methods/base.py
alea_data_generator/perturbations/errors/methods/base_character.py
alea_data_generator/perturbations/errors/methods/base_word.py
alea_data_generator/perturbations/errors/methods/double_character.py
alea_data_generator/perturbations/errors/methods/double_word.py
alea_data_generator/perturbations/errors/methods/filter_character.py
alea_data_generator/perturbations/errors/methods/hyphenate_word.py
alea_data_generator/perturbations/errors/methods/keyboard_character.py
alea_data_generator/perturbations/errors/methods/ocr_character.py
alea_data_generator/perturbations/errors/methods/skip_character.py
alea_data_generator/perturbations/errors/methods/skip_word.py
alea_data_generator/perturbations/errors/methods/swap_character.py
alea_data_generator/perturbations/errors/methods/transpose_character.py
alea_data_generator/perturbations/errors/methods/transpose_word.py
alea_data_generator/perturbations/errors/methods/whitespace_add.py
alea_data_generator/perturbations/errors/methods/whitespace_copy.py
alea_data_generator/perturbations/errors/methods/whitespace_newline.py
alea_data_generator/perturbations/errors/methods/whitespace_remove.py
alea_data_generator/representations/__init__.py
alea_data_generator/samplers/__init__.py
alea_data_generator/samplers/faker_sampler.py
alea_data_generator/templates/__init__.py
alea_data_generator-0.1.2.dist-info/LICENSE
alea_data_generator-0.1.2.dist-info/METADATA
alea_data_generator-0.1.2.dist-info/WHEEL
alea_data_generator-0.1.2.dist-info/RECORD
