Metadata-Version: 2.1
Name: alea-data-generator
Version: 0.1.2
Summary: ALEA low-level data generation techniques (procedural, KL3M)
Home-page: https://aleainstitute.ai/
License: MIT
Keywords: alea,synthetic,data,kl3m
Author: ALEA Institute
Author-email: hello@aleainstitute.ai
Requires-Python: >=3.10,<4.0.0
Classifier: Development Status :: 3 - Alpha
Classifier: Intended Audience :: Developers
Classifier: Intended Audience :: Science/Research
Classifier: License :: OSI Approved :: MIT License
Classifier: Operating System :: OS Independent
Classifier: Programming Language :: Python
Classifier: Programming Language :: Python :: 3
Classifier: Programming Language :: Python :: 3.10
Classifier: Programming Language :: Python :: 3.11
Classifier: Programming Language :: Python :: 3.12
Classifier: Programming Language :: Python :: 3.13
Classifier: Topic :: Scientific/Engineering :: Artificial Intelligence
Classifier: Topic :: Scientific/Engineering :: Information Analysis
Classifier: Topic :: Software Development :: Libraries :: Python Modules
Classifier: Topic :: Utilities
Requires-Dist: faker (>=28.4.1)
Requires-Dist: httpx[http2] (>=0.27.1)
Requires-Dist: jinja2 (>=3.1.4)
Requires-Dist: numpy (>=2.1.1)
Requires-Dist: rapidfuzz (>=3.9.7)
Requires-Dist: scipy (>=1.15.0)
Requires-Dist: tqdm (>=4.66.5)
Project-URL: Repository, https://github.com/alea-institute/alea-data-generator
